mananeras/__init__.py
mananeras/__main__.py
mananeras/dataset/__init__.py
mananeras/dataset/download_articles.py
mananeras/dataset/download_urls.py
mananeras/dataset/extract_dialogs.py
mananeras/entities.py
mananeras/reader.py
mananeras-0.1.4.dist-info/WHEEL
mananeras-0.1.4.dist-info/METADATA
mananeras-0.1.4.dist-info/RECORD
